{
  "rati kaka ni bhaji": {
    "restaurant": "rati kaka ni bhaji",
    "city": "Surat",
    "lat": 21.2094892,
    "lng": 72.8317058,
    "seo_keywords": [
      "rati kaka ni bhaji surat",
      "best food in surat",
      "paneer hhandi",
      "paneer hhandi in surat"
    ]
  },
  "surya dosa": {
    "restaurant": "Surya Dosa",
    "city": "surat",
    "lat": 21.233819,
    "lng": 72.8209081,
    "seo_keywords": [
      "surya dosa surat",
      "best restaurant in surat",
      "restaurant near me",
      "family restaurant in surat",
      "indian food",
      "dosa in surat"
    ]
  }
}